mixturelib/__init__.py
mixturelib/hyper_models.py
mixturelib/local_models.py
mixturelib/mixture.py
mixturelib/regularizers.py
mixturelib-0.4.0.dist-info/LICENSE
mixturelib-0.4.0.dist-info/METADATA
mixturelib-0.4.0.dist-info/WHEEL
mixturelib-0.4.0.dist-info/top_level.txt
mixturelib-0.4.0.dist-info/RECORD
