Metadata-Version: 2.1
Name: mixturelib
Version: 0.4.0
Summary: mixture lib, python package
Home-page: https://github.com/andriygav/MixtureLib
Author: Andrey Grabovoy
Author-email: grabovoy.av@phystech.edu
License: MIT
Platform: UNKNOWN
Requires-Dist: torch (>=1.3.1+cpu)
Requires-Dist: numpy (>=1.18.1)
